ariadna/Caja.py
ariadna/CajaFactory.py
ariadna/CajaMapping.py
ariadna/CajaMutableMapping.py
ariadna/CajaMutableSequence.py
ariadna/CajaMutableSet.py
ariadna/CajaSequence.py
ariadna/CajaSet.py
ariadna/PathSplitter.py
ariadna/__init__.py
ariadna-0.0.1b0.dist-info/LICENSE
ariadna-0.0.1b0.dist-info/METADATA
ariadna-0.0.1b0.dist-info/WHEEL
ariadna-0.0.1b0.dist-info/top_level.txt
ariadna-0.0.1b0.dist-info/RECORD
