Metadata-Version: 2.1
Name: ariadna
Version: 0.0.1b0
Summary: A library of featureful collection objects providing path-like keys
Home-page: https://github.com/dacabdi/ariadna
Author: David Cabrera
Author-email: dacabdi@gmail.com
License: MIT
Download-URL: https://github.com/dacabdi/ariadna/archive/v0.0.1b.tar.gz
Keywords: caja,dict,sequence,path,descriptor,set
Platform: UNKNOWN
Classifier: Intended Audience :: Developers
Classifier: License :: OSI Approved :: MIT License
Classifier: Programming Language :: Python :: 3 :: Only
Requires-Dist: frozendict
